bluos/__init__.py
bluos/_device.py
bluos/_entities.py
bluos-0.1.0.dist-info/LICENSE
bluos-0.1.0.dist-info/METADATA
bluos-0.1.0.dist-info/WHEEL
bluos-0.1.0.dist-info/entry_points.txt
bluos-0.1.0.dist-info/RECORD
