Metadata-Version: 2.1
Name: bluos
Version: 0.1.0
Summary: 
License: MIT
Author: Louis Christ
Author-email: mail@louischrist.de
Requires-Python: >=3.11,<4.0
Classifier: License :: OSI Approved :: MIT License
Classifier: Programming Language :: Python :: 3
Classifier: Programming Language :: Python :: 3.11
Classifier: Programming Language :: Python :: 3.12
Requires-Dist: aiohttp (>=3.9.3,<4.0.0)
Requires-Dist: xmltodict (>=0.13.0,<0.14.0)
